hyko_sdk/__init__.py
hyko_sdk/definitions.py
hyko_sdk/io.py
hyko_sdk/models.py
hyko_sdk/py.typed
hyko_sdk/utils.py
hyko_sdk-4.0.2.dist-info/METADATA
hyko_sdk-4.0.2.dist-info/WHEEL
hyko_sdk-4.0.2.dist-info/RECORD
