Metadata-Version: 2.1
Name: hyko_sdk
Version: 4.0.2
Summary: Hyko's Software Development Kit
Author: Ouassim Abdelmalek Ghribi
Author-email: oag@big-mama.io
Requires-Python: >=3.11.6,<4.0.0
Classifier: Programming Language :: Python :: 3
Classifier: Programming Language :: Python :: 3.12
Requires-Dist: fastapi (>=0.100.1,<0.101.0)
Requires-Dist: httpx[h2] (==0.24.1)
Requires-Dist: numpy (==1.25.2)
Requires-Dist: pillow (>=10.2.0,<11.0.0)
Requires-Dist: pydantic (>=2.5.3,<3.0.0)
Requires-Dist: soundfile (>=0.12.1,<0.13.0)
Requires-Dist: uvicorn[standard] (>=0.25.0,<0.26.0)
